{
    "test_score": 75,
    "train_scores_history": [
        {
            "accuracy": 35,
            "loss": 1.6446204206624915
        },
        {
            "accuracy": 46,
            "loss": 1.3398120899303114
        },
        {
            "accuracy": 54,
            "loss": 1.0988088321693341
        },
        {
            "accuracy": 60,
            "loss": 0.9405651525880355
        },
        {
            "accuracy": 67,
            "loss": 0.8323438954058895
        },
        {
            "accuracy": 67,
            "loss": 0.7368596313052951
        },
        {
            "accuracy": 71,
            "loss": 0.6789350892034342
        },
        {
            "accuracy": 77,
            "loss": 0.6267701288646275
        },
        {
            "accuracy": 80,
            "loss": 0.5810043980580406
        },
        {
            "accuracy": 77,
            "loss": 0.5295513408816526
        },
        {
            "accuracy": 80,
            "loss": 0.49362571051248727
        },
        {
            "accuracy": 84,
            "loss": 0.46358562490187394
        },
        {
            "accuracy": 83,
            "loss": 0.4259308269524627
        }
    ],
    "valid_scores_history": [
        {
            "accuracy": 39,
            "loss": 1.6013410091400146
        },
        {
            "accuracy": 52,
            "loss": 1.1856411695480347
        },
        {
            "accuracy": 61,
            "loss": 1.610612392425537
        },
        {
            "accuracy": 63,
            "loss": 1.5189480781555176
        },
        {
            "accuracy": 67,
            "loss": 1.6987712383270264
        },
        {
            "accuracy": 67,
            "loss": 1.4095230102539062
        },
        {
            "accuracy": 68,
            "loss": 1.2600324153900146
        },
        {
            "accuracy": 70,
            "loss": 1.3959873914718628
        },
        {
            "accuracy": 72,
            "loss": 1.357346773147583
        },
        {
            "accuracy": 73,
            "loss": 0.9529107213020325
        },
        {
            "accuracy": 76,
            "loss": 0.9060689210891724
        },
        {
            "accuracy": 77,
            "loss": 0.7879708409309387
        },
        {
            "accuracy": 73,
            "loss": 0.7246531248092651
        }
    ],
    "best_net_epoch": 11,
    "test_classes_accuracy": {
        "freshripe": 76.92307692307692,
        "freshunripe": 96.96969696969697,
        "overripe": 82.06896551724138,
        "ripe": 72.45508982035928,
        "rotten": 67.42857142857143,
        "unripe": 41.46341463414634
    }
}